yara_gen/__init__.py
yara_gen/constants.py
yara_gen/errors.py
yara_gen/main.py
yara_gen/adapters/__init__.py
yara_gen/adapters/base.py
yara_gen/adapters/csv.py
yara_gen/adapters/factory.py
yara_gen/adapters/huggingface.py
yara_gen/adapters/jsonl.py
yara_gen/adapters/utils.py
yara_gen/cli/__init__.py
yara_gen/cli/args.py
yara_gen/cli/utils.py
yara_gen/cli/commands/__init__.py
yara_gen/cli/commands/generate.py
yara_gen/cli/commands/optimize.py
yara_gen/cli/commands/prepare.py
yara_gen/engine/__init__.py
yara_gen/engine/base.py
yara_gen/engine/factory.py
yara_gen/engine/ngram.py
yara_gen/engine/stub.py
yara_gen/generation/__init__.py
yara_gen/generation/builder.py
yara_gen/generation/deduplication.py
yara_gen/generation/templates.py
yara_gen/generation/writer.py
yara_gen/models/__init__.py
yara_gen/models/adapter_config.py
yara_gen/models/config.py
yara_gen/models/engine_config.py
yara_gen/models/evaluator.py
yara_gen/models/optimization_config.py
yara_gen/models/optimizer.py
yara_gen/models/text.py
yara_gen/optimization/__init__.py
yara_gen/optimization/evaluator.py
yara_gen/optimization/optimizer.py
yara_gen/optimization/splitter.py
yara_gen/utils/__init__.py
yara_gen/utils/config.py
yara_gen/utils/logger.py
yara_gen/utils/progress.py
yara_gen-0.1.5.dist-info/METADATA
yara_gen-0.1.5.dist-info/WHEEL
yara_gen-0.1.5.dist-info/entry_points.txt
yara_gen-0.1.5.dist-info/licenses/LICENSE
yara_gen-0.1.5.dist-info/RECORD
