Metadata-Version: 2.4
Name: yara-gen
Version: 0.1.5
Summary: Automated YARA rule generator for AI Security and Indirect Prompt Injection detection.
Project-URL: Homepage, https://deconvoluteai.com
Project-URL: Repository, https://github.com/deconvolute-labs/yara-gen
Project-URL: Issues, https://github.com/deconvolute-labs/yara-gen/issues
Author-email: David Kirchhoff <david@deconvoluteai.com>
License-Expression: Apache-2.0
License-File: LICENSE
Classifier: Development Status :: 3 - Alpha
Classifier: Intended Audience :: Developers
Classifier: Intended Audience :: Science/Research
Classifier: Intended Audience :: System Administrators
Classifier: License :: OSI Approved :: Apache Software License
Classifier: Operating System :: OS Independent
Classifier: Programming Language :: Python :: 3.13
Classifier: Topic :: Scientific/Engineering :: Artificial Intelligence
Classifier: Topic :: Security
Classifier: Topic :: Software Development :: Libraries :: Python Modules
Requires-Python: >=3.13
Requires-Dist: datasets>=4.5.0
Requires-Dist: jinja2>=3.1.6
Requires-Dist: pydantic>=2.0
Requires-Dist: pyyaml>=6.0.3
Requires-Dist: scikit-learn>=1.8.0
Requires-Dist: types-pyyaml>=6.0.12.20250915
Requires-Dist: yara-python>=4.5.4
